cache_helper/__init__.py
cache_helper/decorators.py
cache_helper/exceptions.py
cache_helper/interfaces.py
cache_helper/settings.py
cache_helper/utils.py
django_cache_helper-1.0.8.dist-info/METADATA
django_cache_helper-1.0.8.dist-info/WHEEL
django_cache_helper-1.0.8.dist-info/top_level.txt
django_cache_helper-1.0.8.dist-info/RECORD
