Metadata-Version: 2.4
Name: django-cache-helper
Version: 1.0.8
Summary: a simple tool for making caching functions, methods, and class methods a little bit easier.
Author-email: YCharts <developers@ycharts.com>
Project-URL: Homepage, https://github.com/ycharts/django_cache_helper
Keywords: cache,django
Classifier: Programming Language :: Python :: 3
Classifier: Environment :: Web Environment
Classifier: Intended Audience :: Developers
Classifier: Operating System :: OS Independent
Classifier: Framework :: Django
Requires-Python: >=3.8
